boids_api/__init__.py
boids_api/__main__.py
boids_api/boids/__init__.py
boids_api/boids/base_model.py
boids_api/boids/behavior_configuration.py
boids_api/boids/boid.py
boids_api/boids/boid_list.py
boids_api/boids/boid_telemetry_event.py
boids_api/boids/cartesian_triple.py
boids_api/boids/error_model.py
boids_api/boids/pagination.py
boids_api/boids/session_configuration.py
boids_api/boids/session_configuration_status.py
boids_api/boids/session_configuration_status_list.py
boids_api/boids/session_state.py
boids_api/boids/session_timestamp.py
boids_api/boids/speed_range.py
boids_api/boids/system_event.py
boids_api/boids/system_event_level.py
boids_api/boids/system_event_list.py
boids_api/boids/system_message_event.py
boids_api/boids/world_configuration.py
boids_api/controllers/__init__.py
boids_api/controllers/boids_controller.py
boids_api/controllers/events_controller.py
boids_api/controllers/pub_sub_topics_controller.py
boids_api/controllers/security_controller.py
boids_api/controllers/sessions_controller.py
boids_api/openapi/openapi.yaml
boids_api/typing_utils.py
boids_api/util.py
boids_api-1.0.3.dist-info/METADATA
boids_api-1.0.3.dist-info/WHEEL
boids_api-1.0.3.dist-info/RECORD
