Metadata-Version: 2.1
Name: boids-api
Version: 1.0.3
Summary: API specification for the Boids application
Home-page: https://github.com/kerrys-learning-lab/boids-api
Author: Kerry Johnson
Author-email: kerry.t.johnson@gmail.com
Classifier: Programming Language :: Python :: 2
Classifier: Programming Language :: Python :: 2.7
Classifier: Programming Language :: Python :: 3
Classifier: Programming Language :: Python :: 3.4
Classifier: Programming Language :: Python :: 3.5
Classifier: Programming Language :: Python :: 3.6
Classifier: Programming Language :: Python :: 3.7
Classifier: Programming Language :: Python :: 3.8
Classifier: Programming Language :: Python :: 3.9
Classifier: Programming Language :: Python :: 3.10
Classifier: Programming Language :: Python :: 3.11
Project-URL: Repository, https://github.com/kerrys-learning-lab/boids-api
